gemini_cli_sdk/__init__.py
gemini_cli_sdk/_errors.py
gemini_cli_sdk/py.typed
gemini_cli_sdk/types.py
gemini_cli_sdk/_internal/__init__.py
gemini_cli_sdk/_internal/client.py
gemini_cli_sdk/_internal/parser/__init__.py
gemini_cli_sdk/_internal/parser/json_parser.py
gemini_cli_sdk/_internal/parser/llm_parser.py
gemini_cli_sdk/_internal/transport/__init__.py
gemini_cli_sdk/_internal/transport/subprocess_cli.py
gemini_cli_sdk-0.1.0.dist-info/METADATA
gemini_cli_sdk-0.1.0.dist-info/WHEEL
gemini_cli_sdk-0.1.0.dist-info/licenses/LICENSE
gemini_cli_sdk-0.1.0.dist-info/RECORD
