Metadata-Version: 2.4
Name: gemini-cli-sdk
Version: 0.1.0
Summary: Python SDK for Gemini CLI - Experimental
Project-URL: Homepage, https://github.com/oneryalcin/gemini-cli-sdk
Project-URL: Documentation, https://github.com/oneryalcin/gemini-cli-sdk
Project-URL: Issues, https://github.com/oneryalcin/gemini-cli-sdk/issues
Author-email: Oner Yalcin <oneryalcin@gmail.com>
License: MIT
License-File: LICENSE
Keywords: ai,cli,gemini,sdk
Classifier: Development Status :: 3 - Alpha
Classifier: Intended Audience :: Developers
Classifier: License :: OSI Approved :: MIT License
Classifier: Programming Language :: Python :: 3
Classifier: Programming Language :: Python :: 3.10
Classifier: Programming Language :: Python :: 3.11
Classifier: Programming Language :: Python :: 3.12
Classifier: Programming Language :: Python :: 3.13
Classifier: Typing :: Typed
Requires-Python: >=3.10
Requires-Dist: anyio>=4.0.0
Requires-Dist: instructor>=1.0.0
Requires-Dist: openai>=1.0.0
Requires-Dist: pydantic>=2.0.0
Requires-Dist: typing-extensions>=4.0.0; python_version < '3.11'
Provides-Extra: dev
Requires-Dist: anyio[trio]>=4.0.0; extra == 'dev'
Requires-Dist: mypy>=1.0.0; extra == 'dev'
Requires-Dist: pytest-asyncio>=0.20.0; extra == 'dev'
Requires-Dist: pytest-cov>=4.0.0; extra == 'dev'
Requires-Dist: pytest>=7.0.0; extra == 'dev'
Requires-Dist: ruff>=0.1.0; extra == 'dev'
